NasrPy/__init__.py
NasrPy-0.2.dist-info/METADATA
NasrPy-0.2.dist-info/WHEEL
NasrPy-0.2.dist-info/top_level.txt
NasrPy-0.2.dist-info/RECORD
