Metadata-Version: 2.1
Name: NasrPy
Version: 0.2
Summary: This is the best encryption library for Nasr
Author: NasrPy
Classifier: Programming Language :: Python :: 3
